insta_feed_checker/__init__.py
insta_feed_checker/checker.py
insta_feed_checker-1.0.0.dist-info/LICENSE
insta_feed_checker-1.0.0.dist-info/METADATA
insta_feed_checker-1.0.0.dist-info/WHEEL
insta_feed_checker-1.0.0.dist-info/top_level.txt
insta_feed_checker-1.0.0.dist-info/RECORD
