Metadata-Version: 2.1
Name: insta-feed-checker
Version: 1.0.0
Summary: The fastest and simplest way to check someone's instagram feeds
Home-page: https://github.com/gibiee/insta-feed-checker
Download-URL: 
Author: gibiee
Author-email: gibiee@naver.com
License: MIT
Keywords: instagram,crawler,crawling,instagram_crawler,instagram_crawling,instacrawler
Classifier: Programming Language :: Python :: 3.6
Classifier: Programming Language :: Python :: 3.7
Classifier: Programming Language :: Python :: 3.8
Classifier: Programming Language :: Python :: 3.9
Classifier: Programming Language :: Python :: 3.10
Classifier: License :: OSI Approved :: MIT License
Classifier: Operating System :: OS Independent
Requires-Python: >=3.6
License-File: LICENSE
Requires-Dist: requests
